{
  "material": "MeshSpecialTerrainNodeMaterial",
  "material_": "MeshSpecialPhongTerrainNodeMaterial",
  "textures_": [
    { "slot":"map",           "tx": "texture_ground8x8"},
    { "slot":"normalMap",     "tx": "texture_ground8x8nm"},
    { "slot":"specularMap",   "tx": "texture_ground8x8metal"}
  ],
  "textures": [
    { "slot":"map",           "tx": "texture_ground8x8"},
    { "slot":"normalMap",     "tx": "texture_ground8x8nm"},
    { "slot":"metalnessMap",  "tx": "texture_ground8x8metal"},
    { "slot":"roughnessMap",  "tx": "texture_ground8x8rough"}
  ],
  "settings": {
    "color": {"r": 1, "g": 1, "b": 1},
    "specular": {"r": 2, "g": 2, "b": 2},
    "shininess":20,
    "metalness": 1.5,
    "roughness": 1.0,
    "envMapIntensity": 2,
    "aoMapIntensity": 1.0
  }
}