{
  "material": "MeshStandardMaterial",
  "textures": [
    { "slot":"map",           "tx": "texture_plane_atlas"},
    { "slot":"normalMap",     "tx": "texture_plane_atlas_normal"},
    { "slot":"metalnessMap",  "tx": "texture_plane_atlas_metalness"},
    { "slot":"roughnessMap",  "tx": "texture_plane_atlas_roughness"}
  ],
  "settings": {
    "color": [1, 1, 1],
    "metalness": 1.0,
    "roughness": 1.0,
    "aoMapIntensity": 1.0
  },
  "shadows": {
    "cast": true,
    "receive": true
  }
}